{
  "_class": "symbolInstance",
  "booleanOperation": -1,
  "clippingMaskMode": 0,
  "do_objectID": "032070ED-A0F9-4026-B266-5592696B35EF",
  "exportOptions": {
    "_class": "exportOptions",
    "do_objectID": "7D90BE44-401D-4B29-AD08-055F117FF730",
    "exportFormats": [
    ],
    "includedLayerIds": [
    ],
    "layerOptions": 0,
    "shouldTrim": false
  },
  "frame": {
    "_class": "rect",
    "constrainProportions": false,
    "do_objectID": "C09D2B75-3092-4A71-ADC5-55B57990169D",
    "height": 40,
    "width": 120,
    "x": 866,
    "y": 17
  },
  "hasClippingMask": false,
  "horizontalSpacing": 0,
  "isFixedToViewport": false,
  "isFlippedHorizontal": false,
  "isFlippedVertical": false,
  "isLocked": false,
  "isVisible": false,
  "layerListExpandedType": 0,
  "name": "Button/*Format*/Icon-Left-40 Copy",
  "nameIsFixed": false,
  "overrideValues": [
  ],
  "resizingConstraint": 45,
  "resizingType": 0,
  "rotation": 0,
  "scale": 1,
  "shouldBreakMaskChain": false,
  "style": {
    "_class": "style",
    "do_objectID": "D4EFC22E-C173-40C0-88E6-1B91957B9379",
    "endMarkerType": 0,
    "miterLimit": 10,
    "startMarkerType": 0,
    "windingRule": 1
  },
  "symbolID": "A4210B37-03B6-4032-89FA-3650DA8DFE4D",
  "verticalSpacing": 0
}