{
  "_class": "symbolInstance",
  "booleanOperation": -1,
  "clippingMaskMode": 0,
  "do_objectID": "230727B0-4378-4D8A-A8ED-29131F82E117",
  "exportOptions": {
    "_class": "exportOptions",
    "do_objectID": "7CCC3901-CF7C-4033-B982-47A7FAFA00FA",
    "exportFormats": [
    ],
    "includedLayerIds": [
    ],
    "layerOptions": 0,
    "shouldTrim": false
  },
  "frame": {
    "_class": "rect",
    "constrainProportions": false,
    "do_objectID": "898F71DF-F8CC-4E87-B72C-DB6D3E4E1A4F",
    "height": 72,
    "width": 1002,
    "x": 315,
    "y": 564
  },
  "hasClippingMask": false,
  "horizontalSpacing": 0,
  "isFixedToViewport": false,
  "isFlippedHorizontal": false,
  "isFlippedVertical": false,
  "isLocked": false,
  "isVisible": true,
  "layerListExpandedType": 0,
  "name": "Listitem/AssessmentItem/Sortable/Active 3",
  "nameIsFixed": true,
  "overrideValues": [
    {
      "_class": "overrideValue",
      "overrideName": "16D4A6B9-A265-4CC0-AEBF-3073476AADCA_stringValue",
      "value": "This is the question stem for item 3: Lorem Ipsum Dolor sit amen"
    }
  ],
  "resizingConstraint": 63,
  "resizingType": 0,
  "rotation": 0,
  "scale": 1,
  "shouldBreakMaskChain": false,
  "style": {
    "_class": "style",
    "do_objectID": "84E03A24-C668-4A0C-82C0-FC7ACB85CEA0",
    "endMarkerType": 0,
    "miterLimit": 10,
    "startMarkerType": 0,
    "windingRule": 1
  },
  "symbolID": "6DD6E3B3-46DE-490D-BB6A-91557380B806",
  "verticalSpacing": 0
}