{
  "_class": "symbolInstance",
  "booleanOperation": -1,
  "clippingMaskMode": 0,
  "do_objectID": "3AF2F34D-DC1B-41B7-9DD4-33D5CD0162E7",
  "exportOptions": {
    "_class": "exportOptions",
    "do_objectID": "D505ACB6-0440-4D48-97B5-896A128CB724",
    "exportFormats": [
    ],
    "includedLayerIds": [
    ],
    "layerOptions": 0,
    "shouldTrim": false
  },
  "frame": {
    "_class": "rect",
    "constrainProportions": false,
    "do_objectID": "819CEA2C-7CFC-4D02-AA3B-090C551A1B90",
    "height": 40,
    "width": 40,
    "x": 946,
    "y": 17
  },
  "hasClippingMask": false,
  "horizontalSpacing": 0,
  "isFixedToViewport": false,
  "isFlippedHorizontal": false,
  "isFlippedVertical": false,
  "isLocked": false,
  "isVisible": true,
  "layerListExpandedType": 0,
  "name": "Icon/med/delete",
  "nameIsFixed": false,
  "overrideValues": [
  ],
  "resizingConstraint": 63,
  "resizingType": 0,
  "rotation": 0,
  "scale": 1,
  "shouldBreakMaskChain": false,
  "style": {
    "_class": "style",
    "do_objectID": "E4BCC23E-BDFD-4982-8DA0-ED98D1C746BE",
    "endMarkerType": 0,
    "miterLimit": 10,
    "startMarkerType": 0,
    "windingRule": 1
  },
  "symbolID": "A0D8118F-6FAB-42D6-B806-668E25DB12CE",
  "verticalSpacing": 0
}