{
  "_class": "symbolInstance",
  "booleanOperation": -1,
  "clippingMaskMode": 0,
  "do_objectID": "8C4203C1-349C-4D1E-8170-CF38D28142F5",
  "exportOptions": {
    "_class": "exportOptions",
    "do_objectID": "D6BFBE58-CB06-46E6-A0B0-5F8814C16575",
    "exportFormats": [
    ],
    "includedLayerIds": [
    ],
    "layerOptions": 0,
    "shouldTrim": false
  },
  "frame": {
    "_class": "rect",
    "constrainProportions": false,
    "do_objectID": "5410F356-9676-4CBC-B566-8D20421C3722",
    "height": 40,
    "width": 232,
    "x": 0,
    "y": 130
  },
  "hasClippingMask": false,
  "horizontalSpacing": 0,
  "isFixedToViewport": false,
  "isFlippedHorizontal": false,
  "isFlippedVertical": false,
  "isLocked": false,
  "isVisible": true,
  "layerListExpandedType": 0,
  "name": "My Assessments/Selected Copy",
  "nameIsFixed": false,
  "overrideValues": [
  ],
  "resizingConstraint": 9,
  "resizingType": 0,
  "rotation": 0,
  "scale": 1,
  "shouldBreakMaskChain": false,
  "style": {
    "_class": "style",
    "do_objectID": "B52DDEC8-C864-43D6-8084-5F00357B2E75",
    "endMarkerType": 0,
    "miterLimit": 10,
    "startMarkerType": 0,
    "windingRule": 1
  },
  "symbolID": "53ECF455-15B6-469B-874B-59409019FEBC",
  "verticalSpacing": 0
}