{
  "_class": "symbolInstance",
  "booleanOperation": -1,
  "clippingMaskMode": 0,
  "do_objectID": "FF79EF49-BE2B-4382-990D-986AA5BE82A1",
  "exportOptions": {
    "_class": "exportOptions",
    "do_objectID": "2A06C881-28B6-43D6-A146-425D1640ED4B",
    "exportFormats": [
    ],
    "includedLayerIds": [
    ],
    "layerOptions": 0,
    "shouldTrim": false
  },
  "frame": {
    "_class": "rect",
    "constrainProportions": false,
    "do_objectID": "18F843C1-0FA5-498F-B4B2-4F2F95F2B2CA",
    "height": 40,
    "width": 40,
    "x": 0,
    "y": 14
  },
  "hasClippingMask": false,
  "horizontalSpacing": 0,
  "isFixedToViewport": false,
  "isFlippedHorizontal": false,
  "isFlippedVertical": false,
  "isLocked": false,
  "isVisible": true,
  "layerListExpandedType": 0,
  "name": "Icon/sml/chevron-down-2",
  "nameIsFixed": false,
  "overrideValues": [
  ],
  "resizingConstraint": 63,
  "resizingType": 0,
  "rotation": 0,
  "scale": 1,
  "shouldBreakMaskChain": false,
  "style": {
    "_class": "style",
    "do_objectID": "332BC60F-5237-4373-9A19-4421D2BEA9B1",
    "endMarkerType": 0,
    "miterLimit": 10,
    "startMarkerType": 0,
    "windingRule": 1
  },
  "symbolID": "E7D64AFF-C314-4482-81B8-41B43DC9626F",
  "verticalSpacing": 0
}