{
  "_class": "symbolInstance",
  "booleanOperation": -1,
  "clippingMaskMode": 0,
  "do_objectID": "E6B8CB40-13E2-49F3-8E79-7AE181497E81",
  "exportOptions": {
    "_class": "exportOptions",
    "do_objectID": "6A2E6101-BBA6-4638-810D-8E9C483639C1",
    "exportFormats": [
    ],
    "includedLayerIds": [
    ],
    "layerOptions": 0,
    "shouldTrim": false
  },
  "frame": {
    "_class": "rect",
    "constrainProportions": false,
    "do_objectID": "9F173639-6610-47D1-B402-DA68B4821D5D",
    "height": 65,
    "width": 1052,
    "x": 274,
    "y": 430
  },
  "hasClippingMask": false,
  "horizontalSpacing": 0,
  "isFixedToViewport": false,
  "isFlippedHorizontal": false,
  "isFlippedVertical": false,
  "isLocked": false,
  "isVisible": true,
  "layerListExpandedType": 0,
  "name": "ListItem/Custom Assessment Copy 2",
  "nameIsFixed": false,
  "overrideValues": [
    {
      "_class": "overrideValue",
      "overrideName": "9B2C2CEB-2DAA-428F-9226-BA29EA970615_symbolID",
      "value": ""
    }
  ],
  "resizingConstraint": 63,
  "resizingType": 0,
  "rotation": 0,
  "scale": 1,
  "shouldBreakMaskChain": false,
  "style": {
    "_class": "style",
    "do_objectID": "AF945ED6-16EE-4358-B1D6-A4CBD081F4F0",
    "endMarkerType": 0,
    "miterLimit": 10,
    "startMarkerType": 0,
    "windingRule": 1
  },
  "symbolID": "EA419076-04A6-4F4B-BB84-28270D60180B",
  "verticalSpacing": 0
}