{
  "_class": "symbolInstance",
  "booleanOperation": -1,
  "clippingMaskMode": 0,
  "do_objectID": "F7668EED-810B-4B9B-A5AF-41F4752A10D3",
  "exportOptions": {
    "_class": "exportOptions",
    "do_objectID": "52EF41D4-5368-4BFF-9511-D889205F6380",
    "exportFormats": [
    ],
    "includedLayerIds": [
    ],
    "layerOptions": 0,
    "shouldTrim": false
  },
  "frame": {
    "_class": "rect",
    "constrainProportions": false,
    "do_objectID": "BC6CF4E8-6FA1-4DBD-804C-F8080ABA73DD",
    "height": 80,
    "width": 80,
    "x": 0,
    "y": 0
  },
  "hasClippingMask": false,
  "horizontalSpacing": 0,
  "isFixedToViewport": false,
  "isFlippedHorizontal": false,
  "isFlippedVertical": false,
  "isLocked": false,
  "isVisible": true,
  "layerListExpandedType": 0,
  "name": "My Assessments Icon",
  "nameIsFixed": false,
  "overrideValues": [
  ],
  "resizingConstraint": 63,
  "resizingType": 0,
  "rotation": 0,
  "scale": 2,
  "shouldBreakMaskChain": false,
  "style": {
    "_class": "style",
    "blur": {
      "_class": "blur",
      "center": "{0.5, 0.5}",
      "do_objectID": "C2BCF500-6620-447E-A1FE-481886E49FBA",
      "isEnabled": false,
      "motionAngle": 0,
      "radius": 20,
      "saturation": 1,
      "type": 0
    },
    "do_objectID": "B99C03A4-16A1-4ADE-963D-092F7F5EC63E",
    "endMarkerType": 0,
    "miterLimit": 10,
    "startMarkerType": 0,
    "windingRule": 1
  },
  "symbolID": "4F823A5F-8D03-42EF-AD25-A8A2CB1A5E54",
  "verticalSpacing": 0
}