{
  "_class": "symbolInstance",
  "booleanOperation": -1,
  "clippingMaskMode": 0,
  "do_objectID": "462317AA-2596-445B-9714-141501016F16",
  "exportOptions": {
    "_class": "exportOptions",
    "do_objectID": "46B9C3C2-7699-494A-AA0E-34D5E3FB8EA7",
    "exportFormats": [
    ],
    "includedLayerIds": [
    ],
    "layerOptions": 0,
    "shouldTrim": false
  },
  "frame": {
    "_class": "rect",
    "constrainProportions": false,
    "do_objectID": "5012B499-6B97-4C42-8BD8-347ED5DFBF25",
    "height": 72,
    "width": 1037,
    "x": 281,
    "y": 484
  },
  "hasClippingMask": false,
  "horizontalSpacing": 0,
  "isFixedToViewport": false,
  "isFlippedHorizontal": false,
  "isFlippedVertical": false,
  "isLocked": false,
  "isVisible": true,
  "layerListExpandedType": 0,
  "name": "Drop Zone Default 2",
  "nameIsFixed": true,
  "overrideValues": [
  ],
  "resizingConstraint": 63,
  "resizingType": 0,
  "rotation": 0,
  "scale": 1,
  "shouldBreakMaskChain": false,
  "style": {
    "_class": "style",
    "do_objectID": "6DA134F7-C3E0-434B-B30C-F3D41F70EC75",
    "endMarkerType": 0,
    "miterLimit": 10,
    "startMarkerType": 0,
    "windingRule": 1
  },
  "symbolID": "DC4A1D17-38F7-4BD7-A3C1-2232537ADB67",
  "verticalSpacing": 0
}