{
  "_class": "text",
  "attributedString": {
    "_class": "attributedString",
    "attributes": [
      {
        "_class": "stringAttribute",
        "attributes": {
          "MSAttributedStringColorAttribute": {
            "_class": "color",
            "alpha": 1,
            "blue": 0.2470588235,
            "green": 0.2470588235,
            "red": 0.2392156863
          },
          "MSAttributedStringFontAttribute": {
            "_class": "fontDescriptor",
            "attributes": {
              "name": "SlatePro-Medium",
              "size": 27.20000076293945
            }
          },
          "kerning": 0.3777778,
          "paragraphStyle": {
            "_class": "paragraphStyle",
            "alignment": 0,
            "allowsDefaultTighteningForTruncation": 0,
            "maximumLineHeight": 28,
            "minimumLineHeight": 28
          }
        },
        "length": 30,
        "location": 0
      }
    ],
    "string": "Editing an HMH Curriculum Item"
  },
  "automaticallyDrawOnUnderlyingPath": false,
  "booleanOperation": 0,
  "clippingMaskMode": 0,
  "do_objectID": "90061AEB-8AF2-4A70-ADE7-09DC201C4677",
  "dontSynchroniseWithSymbol": false,
  "exportOptions": {
    "_class": "exportOptions",
    "do_objectID": "D1FF4BEE-9626-4DB2-A20E-A92434C31128",
    "exportFormats": [
    ],
    "includedLayerIds": [
    ],
    "layerOptions": 0,
    "shouldTrim": false
  },
  "frame": {
    "_class": "rect",
    "constrainProportions": false,
    "do_objectID": "C1D39568-1E0F-4B61-A493-7EB9F4CD780A",
    "height": 28,
    "width": 575.969387755102,
    "x": 24,
    "y": 22
  },
  "glyphBounds": "{{1, 5}, {379, 24}}",
  "hasClippingMask": false,
  "isFixedToViewport": false,
  "isFlippedHorizontal": false,
  "isFlippedVertical": false,
  "isLocked": false,
  "isVisible": true,
  "layerListExpandedType": 0,
  "lineSpacingBehaviour": 2,
  "name": "Title",
  "nameIsFixed": true,
  "resizingConstraint": 27,
  "resizingType": 0,
  "rotation": 0,
  "shouldBreakMaskChain": false,
  "style": {
    "_class": "style",
    "do_objectID": "F86D325B-BB95-4075-B1F5-937CA0C91E7F",
    "endMarkerType": 0,
    "miterLimit": 10,
    "startMarkerType": 0,
    "textStyle": {
      "_class": "textStyle",
      "do_objectID": "068A6412-FD83-4BDA-ADB8-65B36ED90198",
      "encodedAttributes": {
        "MSAttributedStringColorAttribute": {
          "_class": "color",
          "alpha": 1,
          "blue": 0.2470588235,
          "green": 0.2470588235,
          "red": 0.2392156863
        },
        "MSAttributedStringFontAttribute": {
          "_class": "fontDescriptor",
          "attributes": {
            "name": "SlatePro-Medium",
            "size": 27.20000076293945
          }
        },
        "kerning": 0.3777778,
        "paragraphStyle": {
          "_class": "paragraphStyle",
          "alignment": 0,
          "allowsDefaultTighteningForTruncation": 0,
          "maximumLineHeight": 28,
          "minimumLineHeight": 28
        }
      },
      "verticalAlignment": 0
    },
    "windingRule": 1
  },
  "textBehaviour": 1,
  "userInfo": {
    "com.animaapp.stc-sketch-plugin": {
      "kModelPropertiesKey": {
      }
    }
  }
}